otterai/__init__.py
otterai/otterai.py
otterai_py-0.0.2.dist-info/LICENSE
otterai_py-0.0.2.dist-info/METADATA
otterai_py-0.0.2.dist-info/WHEEL
otterai_py-0.0.2.dist-info/top_level.txt
otterai_py-0.0.2.dist-info/RECORD
