Metadata-Version: 2.2
Name: otterai-py
Version: 0.0.2
Summary: Unofficial Otter.ai Python API
License: MIT
Project-URL: Homepage, https://github.com/ChocoTonic/otterai-py
Project-URL: Repository, https://github.com/ChocoTonic/otterai-py
Project-URL: Issues, https://github.com/ChocoTonic/otterai-py/issues
Keywords: api,otter,otterai,otterai-py,python
Requires-Python: >=3.9
License-File: LICENSE
Requires-Dist: python-dotenv>=1.0.1
Requires-Dist: requests-toolbelt>=1.0.0
Requires-Dist: requests>=2.32.3
Requires-Dist: tenacity>=8.2.2
Provides-Extra: dev
Requires-Dist: black>=23.9.1; extra == "dev"
Requires-Dist: pre-commit>=4.1.0; extra == "dev"
Requires-Dist: pytest-cov>=5.0.0; extra == "dev"
Requires-Dist: pytest>=8.3.4; extra == "dev"
Requires-Dist: python-dotenv>=1.0.1; extra == "dev"
